dockit/__init__.py
dockit/app.py
dockit/docker-compose.yml
dockit/dockit.spec
dockit/requirements.txt
dockit/commands/__init__.py
dockit/commands/about.py
dockit/commands/add_service.py
dockit/commands/delete_service.py
dockit/commands/generator.py
dockit/commands/init.py
dockit/commands/publish.py
dockit/commands/version.py
dockit/services/__init__.py
dockit/services/mailhog/service.json
dockit/services/mongo/service.json
dockit/services/mysql/service.json
dockit/services/nginx/service.json
dockit/services/nginx/conf/latest/laravel.conf
dockit/services/nginx/conf/latest/node.conf
dockit/services/node/service.json
dockit/services/php/service.json
dockit/services/php/conf/7.4/php.ini
dockit/services/php/conf/7.4/xdebug.ini
dockit/services/php/conf/8.0/php.ini
dockit/services/php/conf/8.0/xdebug.ini
dockit/services/php/conf/8.1/php.ini
dockit/services/php/conf/8.1/xdebug.ini
dockit/services/php/conf/8.2/php.ini
dockit/services/php/conf/8.2/xdebug.ini
dockit/services/php/conf/8.3/php.ini
dockit/services/php/conf/8.3/xdebug.ini
dockit/services/php/conf/8.4/php.ini
dockit/services/php/conf/8.4/xdebug.ini
dockit/services/phpmyadmin/service.json
dockit/services/postgres/service.json
dockit/services/redis/service.json
dockit/templates/Dockerfile.j2
dockit/templates/docker-compose.yml.j2
dockit/templates/skeletons/build_version.json
dockit/templates/skeletons/image_base.json
dockit/tests/test_generator.py
dockit/tests/test_publish_command.py
dockit/tests/test_service_manager.py
dockit/utilities/__init__.py
dockit/utilities/debugger.py
dockit/utilities/docker_manager.py
dockit/utilities/gitignore_manager.py
dockit/utilities/messenger.py
dockit/utilities/path_resolver.py
dockit/utilities/service_manager.py
dockit_cli-2.2.3.dist-info/METADATA
dockit_cli-2.2.3.dist-info/WHEEL
dockit_cli-2.2.3.dist-info/entry_points.txt
dockit_cli-2.2.3.dist-info/licenses/LICENSE
dockit_cli-2.2.3.dist-info/RECORD
