Metadata-Version: 2.4
Name: dockit-cli
Version: 2.2.3
Summary: A Docker management tool
Author-email: Islam Zekry <theizekry@gmail.com>
License-Expression: MIT
License-File: LICENSE
Classifier: Development Status :: 4 - Beta
Classifier: Intended Audience :: Developers
Classifier: License :: OSI Approved :: MIT License
Classifier: Programming Language :: Python :: 3.11
Classifier: Topic :: Software Development :: Libraries :: Python Modules
Requires-Python: >=3.11
Requires-Dist: click<8.2.0,>=8.0.0
Requires-Dist: docker>=6.0.0
Requires-Dist: jinja2>=3.0.0
Requires-Dist: pyyaml>=6.0.0
Requires-Dist: questionary>=1.10.0
Requires-Dist: rich>=10.0.0
Requires-Dist: typer>=0.9.0
